feedfilter/__init__.py
feedfilter/feed_filter.py
feedfilter/logger.py
feedfilter-1.1.0.dist-info/LICENSE
feedfilter-1.1.0.dist-info/METADATA
feedfilter-1.1.0.dist-info/WHEEL
feedfilter-1.1.0.dist-info/entry_points.txt
feedfilter-1.1.0.dist-info/RECORD
