Metadata-Version: 2.1
Name: feedfilter
Version: 1.1.0
Summary: Modify RSS/Atom feeds
Home-page: https://gitlab.com/jim_bauer/feed-filter
License: GPL-3.0-or-later
Keywords: rss,atom
Author: Jim Bauer
Requires-Python: >=3.10,<4.0
Classifier: Environment :: Console
Classifier: License :: OSI Approved :: GNU General Public License v3 or later (GPLv3+)
Classifier: Programming Language :: Python :: 3
Classifier: Programming Language :: Python :: 3.10
Classifier: Programming Language :: Python :: 3.11
Classifier: Topic :: Text Processing :: Filters
Requires-Dist: bs4 (>=0.0.1,<0.0.2)
Requires-Dist: configparser (>=5.3.0,<6.0.0)
Requires-Dist: feedgen (>=0.9.0,<0.10.0)
Requires-Dist: feedparser (>=6.0.10,<7.0.0)
Requires-Dist: pytz (>=2022.6)
Requires-Dist: requests (>=2.28.1,<3.0.0)
Requires-Dist: sgmllib3k (>=1.0.0,<2.0.0)
Requires-Dist: xdg-base-dirs (>=6.0.0,<7.0.0)
Project-URL: Repository, https://gitlab.com/jim_bauer/feed-filter
